src/models/__init__.py
src/models/common.py
src/models/experimental.py
src/models/yolo.py
src/utils/__init__.py
src/utils/activations.py
src/utils/add_nms.py
src/utils/autoanchor.py
src/utils/aws/__init__.py
src/utils/aws/mime.sh
src/utils/aws/resume.py
src/utils/aws/userdata.sh
src/utils/datasets.py
src/utils/general.py
src/utils/google_app_engine/Dockerfile
src/utils/google_app_engine/additional_requirements.txt
src/utils/google_app_engine/app.yaml
src/utils/google_utils.py
src/utils/loss.py
src/utils/metrics.py
src/utils/plots.py
src/utils/torch_utils.py
src/utils/wandb_logging/__init__.py
src/utils/wandb_logging/log_dataset.py
src/utils/wandb_logging/wandb_utils.py
yolov7x-0.1.1.dist-info/METADATA
yolov7x-0.1.1.dist-info/WHEEL
yolov7x-0.1.1.dist-info/RECORD
