Metadata-Version: 2.1
Name: yolov7x
Version: 0.1.1
Summary: 
Author: Doohoon Kim
Author-email: me@doohoon.kim
Requires-Python: >=3.6,<4.0
Classifier: Programming Language :: Python :: 3
Classifier: Programming Language :: Python :: 3.6
Classifier: Programming Language :: Python :: 3.7
Classifier: Programming Language :: Python :: 3.8
Classifier: Programming Language :: Python :: 3.9
Classifier: Programming Language :: Python :: 3.10
Classifier: Programming Language :: Python :: 3.11
Requires-Dist: ipython (>=8.12.0,<9.0.0)
Requires-Dist: matplotlib (>=3.2.2)
Requires-Dist: numpy (>=1.18.5,<1.24.0)
Requires-Dist: opencv-python (>=4.1.1)
Requires-Dist: pandas (>=1.1.4)
Requires-Dist: pillow (>=7.1.2)
Requires-Dist: protobuf (<4.21.3)
Requires-Dist: psutil (>=5.9.5,<6.0.0)
Requires-Dist: pyyaml (>=5.3.1)
Requires-Dist: requests (>=2.23.0)
Requires-Dist: scipy (>=1.4.1)
Requires-Dist: seaborn (>=0.11.0)
Requires-Dist: tensorboard (>=2.4.1)
Requires-Dist: thop (>=0.1.1.post2209072238,<0.2.0)
Requires-Dist: torch (>=1.7.0,!=1.12.0)
Requires-Dist: torchvision (>=0.8.1,!=0.13.0)
Requires-Dist: tqdm (>=4.41.0)
